chimera/__init__.py
chimera/fm.py
chimera_exo-1.0.dist-info/METADATA
chimera_exo-1.0.dist-info/WHEEL
chimera_exo-1.0.dist-info/top_level.txt
chimera_exo-1.0.dist-info/RECORD
