Metadata-Version: 2.1
Name: chimera-exo
Version: 1.0
Summary: exoplanet code for transmission and emission spectroscopy
Home-page: UNKNOWN
Author: Mike R. Line
Author-email: mrline@asu.edu
License: GPL-3.0
Download-URL: https://github.com/mrline/chimera
Platform: UNKNOWN
Classifier: Intended Audience :: Science/Research
Classifier: License :: OSI Approved :: BSD License
Classifier: Operating System :: OS Independent
Classifier: Programming Language :: Python
Classifier: Programming Language :: Python :: 3
Classifier: Topic :: Scientific/Engineering :: Astronomy
Classifier: Topic :: Software Development :: Libraries :: Python Modules
Requires-Dist: numpy
Requires-Dist: numba
Requires-Dist: joblib
Requires-Dist: photutils
Requires-Dist: astropy
Requires-Dist: scipy
Requires-Dist: pysynphot
Requires-Dist: h5py
